pydantic_graph_persistence/__init__.py
pydantic_graph_persistence/latest.py
pydantic_graph_persistence-0.1.1.dist-info/METADATA
pydantic_graph_persistence-0.1.1.dist-info/WHEEL
pydantic_graph_persistence-0.1.1.dist-info/licenses/LICENSE
pydantic_graph_persistence-0.1.1.dist-info/RECORD
